averbis/__init__.py
averbis/__version__.py
averbis/core/__init__.py
averbis/core/_rest_client.py
averbis/highlighting/__init__.py
averbis/highlighting/_utils.py
averbis_python_api-0.17.0.dist-info/licenses/LICENSE
averbis_python_api-0.17.0.dist-info/METADATA
averbis_python_api-0.17.0.dist-info/WHEEL
averbis_python_api-0.17.0.dist-info/top_level.txt
averbis_python_api-0.17.0.dist-info/RECORD
