Metadata-Version: 2.4
Name: averbis-python-api
Version: 0.17.0
Summary: Averbis REST API client for Python.
Author: Averbis GmbH
License: Apache License, Version 2.0. Copyright Averbis GmbH
Project-URL: Issues, https://github.com/averbis/averbis-python-api/issues
Project-URL: Repository, https://github.com/averbis/averbis-python-api
Project-URL: Documentation, https://averbis-python-api.readthedocs.io/en/latest/?badge=latest
Classifier: Development Status :: 4 - Beta
Classifier: Programming Language :: Python :: 3 :: Only
Classifier: Programming Language :: Python :: 3.9
Classifier: Programming Language :: Python :: 3.10
Classifier: Programming Language :: Python :: 3.11
Classifier: Programming Language :: Python :: 3.12
Classifier: Programming Language :: Python :: 3.13
Classifier: License :: OSI Approved :: Apache Software License
Requires-Python: >=3.9.0
License-File: LICENSE
Requires-Dist: requests
Requires-Dist: types-requests
Requires-Dist: dkpro-cassis
Requires-Dist: ijson
Dynamic: license-file
